{"cameraMode":{"drawMode":0,"name":"Shaded","section":"Shading Mode"},"sceneLighting":true,"audioPlay":false,"sceneViewState":{"showFog":true,"showMaterialUpdate":false,"showSkybox":true,"showFlares":true,"showImageEffects":true,"showParticleSystems":true},"in2DMode":false,"pivot":{"x":-0.9847948551177979,"y":1.2362053394317628,"z":-9.180359840393067},"rotation":{"x":-0.08685655146837235,"y":0.9001484513282776,"z":-0.21058307588100434,"w":-0.37127289175987246},"size":5.526803016662598,"orthographic":false}